competitions/__init__.py
competitions/clip_score.py
competitions/competition_utils.py
competitions/run_eval.py
vbench/VBench_full_info.json
vbench/__init__.py
vbench/aesthetic_quality.py
vbench/appearance_style.py
vbench/background_consistency.py
vbench/color.py
vbench/distributed.py
vbench/dynamic_degree.py
vbench/human_action.py
vbench/imaging_quality.py
vbench/motion_smoothness.py
vbench/multiple_objects.py
vbench/object_class.py
vbench/overall_consistency.py
vbench/scene.py
vbench/spatial_relationship.py
vbench/subject_consistency.py
vbench/temporal_flickering.py
vbench/temporal_style.py
vbench/utils.py
vbench/cli/__init__.py
vbench/cli/evaluate.py
vbench/cli/static_filter.py
vbench/cli/vbench.py
vbench/launch/__init__.py
vbench/launch/evaluate.py
vbench/third_party/__init__.py
vbench/third_party/grit_model.py
vbench/third_party/RAFT/__init__.py
vbench/third_party/RAFT/chairs_split.txt
vbench/third_party/RAFT/core/__init__.py
vbench/third_party/RAFT/core/corr.py
vbench/third_party/RAFT/core/datasets.py
vbench/third_party/RAFT/core/extractor.py
vbench/third_party/RAFT/core/raft.py
vbench/third_party/RAFT/core/update.py
vbench/third_party/RAFT/core/utils_core/__init__.py
vbench/third_party/RAFT/core/utils_core/augmentor.py
vbench/third_party/RAFT/core/utils_core/flow_viz.py
vbench/third_party/RAFT/core/utils_core/frame_utils.py
vbench/third_party/RAFT/core/utils_core/utils.py
vbench/third_party/ViCLIP/__init__.py
vbench/third_party/ViCLIP/simple_tokenizer.py
vbench/third_party/ViCLIP/viclip.py
vbench/third_party/ViCLIP/viclip_text.py
vbench/third_party/ViCLIP/viclip_vision.py
vbench/third_party/amt/__init__.py
vbench/third_party/amt/environment.yaml
vbench/third_party/amt/train.py
vbench/third_party/amt/benchmarks/__init__.py
vbench/third_party/amt/benchmarks/adobe240.py
vbench/third_party/amt/benchmarks/gopro.py
vbench/third_party/amt/benchmarks/snu_film.py
vbench/third_party/amt/benchmarks/speed_parameters.py
vbench/third_party/amt/benchmarks/ucf101.py
vbench-0.1.5.dist-info/LICENSE
vbench-0.1.5.dist-info/METADATA
vbench-0.1.5.dist-info/WHEEL
vbench-0.1.5.dist-info/entry_points.txt
vbench-0.1.5.dist-info/top_level.txt
vbench-0.1.5.dist-info/RECORD
