Metadata-Version: 2.1
Name: vbench
Version: 0.1.5
Summary: Video generation benchmark
License: Apache Software License 2.0
Project-URL: Source, https://github.com/Vchitect/VBench
License-File: LICENSE
